splitter_praveenx23417897/__init__.py
splitter_praveenx23417897/operations.py
splitter_praveenx23417897-0.1.dist-info/METADATA
splitter_praveenx23417897-0.1.dist-info/WHEEL
splitter_praveenx23417897-0.1.dist-info/top_level.txt
splitter_praveenx23417897-0.1.dist-info/RECORD
