Metadata-Version: 2.2
Name: splitter-praveenx23417897
Version: 0.1
Summary: A simple library for addition, subtraction, division
Home-page: https://github.com/praveen/splitter-praveenx23417897
Author: praveen
Author-email: x23417897@student.ncirl.ie
Classifier: Programming Language :: Python :: 3
Classifier: License :: OSI Approved :: MIT License
Classifier: Operating System :: OS Independent
Requires-Python: >=3.6
Dynamic: author
Dynamic: author-email
Dynamic: classifier
Dynamic: description
Dynamic: description-content-type
Dynamic: home-page
Dynamic: requires-python
Dynamic: summary
